topsis/__init__.py
topsis/topsis.py
Topsis_Yashvi_102203529-1.0.0.dist-info/LICENSE
Topsis_Yashvi_102203529-1.0.0.dist-info/METADATA
Topsis_Yashvi_102203529-1.0.0.dist-info/WHEEL
Topsis_Yashvi_102203529-1.0.0.dist-info/entry_points.txt
Topsis_Yashvi_102203529-1.0.0.dist-info/top_level.txt
Topsis_Yashvi_102203529-1.0.0.dist-info/RECORD
